MANIFEST.in
README.md
requirements.txt
setup.py
redshift_console/__init__.py
redshift_console/__main__.py
redshift_console/app.py
redshift_console/queries.yaml
redshift_console/redshift.py
redshift_console/settings.py
redshift_console.egg-info/PKG-INFO
redshift_console.egg-info/SOURCES.txt
redshift_console.egg-info/dependency_links.txt
redshift_console.egg-info/entry_points.txt
redshift_console.egg-info/pbr.json
redshift_console.egg-info/requires.txt
redshift_console.egg-info/top_level.txt
redshift_console/static/dist/404.html
redshift_console/static/dist/index.html
redshift_console/static/dist/robots.txt
redshift_console/static/dist/bower_components/bootstrap/Gruntfile.js
redshift_console/static/dist/bower_components/bootstrap/package.js
redshift_console/static/dist/bower_components/bootstrap/dist/js/bootstrap.js
redshift_console/static/dist/bower_components/bootstrap/dist/js/bootstrap.min.js
redshift_console/static/dist/bower_components/bootstrap/dist/js/npm.js
redshift_console/static/dist/bower_components/bootstrap/grunt/bs-commonjs-generator.js
redshift_console/static/dist/bower_components/bootstrap/grunt/bs-glyphicons-data-generator.js
redshift_console/static/dist/bower_components/bootstrap/grunt/bs-lessdoc-parser.js
redshift_console/static/dist/bower_components/bootstrap/grunt/bs-raw-files-generator.js
redshift_console/static/dist/bower_components/bootstrap/js/affix.js
redshift_console/static/dist/bower_components/bootstrap/js/alert.js
redshift_console/static/dist/bower_components/bootstrap/js/button.js
redshift_console/static/dist/bower_components/bootstrap/js/carousel.js
redshift_console/static/dist/bower_components/bootstrap/js/collapse.js
redshift_console/static/dist/bower_components/bootstrap/js/dropdown.js
redshift_console/static/dist/bower_components/bootstrap/js/modal.js
redshift_console/static/dist/bower_components/bootstrap/js/popover.js
redshift_console/static/dist/bower_components/bootstrap/js/scrollspy.js
redshift_console/static/dist/bower_components/bootstrap/js/tab.js
redshift_console/static/dist/bower_components/bootstrap/js/tooltip.js
redshift_console/static/dist/bower_components/bootstrap/js/transition.js
redshift_console/static/dist/bower_components/es6-promise/promise.js
