Metadata-Version: 1.1
Name: redshift-console
Version: 0.1.3
Summary: Monitor and manage your Redshift cluster.
Home-page: http://github.com/EverythingMe/redshift_console/
Author: Arik Fraimovich, Oren Itamar
Author-email: opensource@everything.me
License: Apache
Platform: UNKNOWN
Classifier: License :: OSI Approved :: Apache Software License
Classifier: Programming Language :: Python
